acetone_nnet/__init__.py
acetone_nnet/cli/compare.py
acetone_nnet/cli/generate.py
acetone_nnet/debug/__init__.py
acetone_nnet/debug/debug_keras.py
acetone_nnet/debug/debug_onnx.py
acetone_nnet/debug/debug_tools.py
acetone_nnet/generator/Layer.py
acetone_nnet/generator/__init__.py
acetone_nnet/generator/activation_functions.py
acetone_nnet/generator/cuda.py
acetone_nnet/generator/neural_network.py
acetone_nnet/generator/layers/AddBias.py
acetone_nnet/generator/layers/Dot.py
acetone_nnet/generator/layers/__init__.py
acetone_nnet/generator/layers/activation_layers/ActivationLayer.py
acetone_nnet/generator/layers/activation_layers/__init__.py
acetone_nnet/generator/layers/batch_normalization/BatchNormalization.py
acetone_nnet/generator/layers/batch_normalization/BatchNormalizationDefault.py
acetone_nnet/generator/layers/batch_normalization/__init__.py
acetone_nnet/generator/layers/broadcast/Broadcast.py
acetone_nnet/generator/layers/broadcast/__init__.py
acetone_nnet/generator/layers/broadcast/add/Add.py
acetone_nnet/generator/layers/broadcast/add/AddDefault.py
acetone_nnet/generator/layers/broadcast/add/__init__.py
acetone_nnet/generator/layers/broadcast/average/Average.py
acetone_nnet/generator/layers/broadcast/average/AverageDefault.py
acetone_nnet/generator/layers/broadcast/average/__init__.py
acetone_nnet/generator/layers/broadcast/divide/Divide.py
acetone_nnet/generator/layers/broadcast/divide/DivideDefault.py
acetone_nnet/generator/layers/broadcast/divide/__init__.py
acetone_nnet/generator/layers/broadcast/maximum/Maximum.py
acetone_nnet/generator/layers/broadcast/maximum/MaximumDefault.py
acetone_nnet/generator/layers/broadcast/maximum/__init__.py
acetone_nnet/generator/layers/broadcast/minimum/Minimum.py
acetone_nnet/generator/layers/broadcast/minimum/MinimumDefault.py
acetone_nnet/generator/layers/broadcast/minimum/__init__.py
acetone_nnet/generator/layers/broadcast/multiply/Multiply.py
acetone_nnet/generator/layers/broadcast/multiply/MultiplyDefault.py
acetone_nnet-1.0.post1.dist-info/licenses/AUTHORS.md
acetone_nnet-1.0.post1.dist-info/licenses/LICENSE
acetone_nnet-1.0.post1.dist-info/METADATA
acetone_nnet-1.0.post1.dist-info/WHEEL
acetone_nnet-1.0.post1.dist-info/entry_points.txt
acetone_nnet-1.0.post1.dist-info/top_level.txt
acetone_nnet-1.0.post1.dist-info/RECORD
