Metadata-Version: 2.4
Name: acetone-nnet
Version: 1.0.post1
Summary: Predictable programming framework for ML applications in safety-critical systems.
Author-email: Yanis AIT-AISSA <Yanis.AIT-AISSA@student.isae-supaero.fr>, Thomas CARLE <Thomas.Carle@irit.fr>, Iryna DE ALBUQUERQUE SILVA <Iryna.De_Albuquerque_Silva@onera.fr>, Adrien GAUFFRIAU <Adrien.Gauffriau@airbus.com>, Benjamin LESAGE <benjamin.lesage@onera.fr>, Claire PAGETTI <Claire.Pagetti@onera.fr>
Project-URL: Repository, https://github.com/onera/acetone/
Project-URL: Bug Tracker, https://github.com/onera/acetone/issues
Classifier: Development Status :: 3 - Alpha
Classifier: Programming Language :: Python :: 3
Classifier: Programming Language :: C
Classifier: License :: OSI Approved :: GNU Lesser General Public License v3 (LGPLv3)
Classifier: Operating System :: OS Independent
Classifier: Intended Audience :: Science/Research
Classifier: Topic :: Software Development :: Code Generators
Classifier: Topic :: Software Development :: Embedded Systems
Classifier: Topic :: Scientific/Engineering :: Artificial Intelligence
Requires-Python: >=3.10
License-File: LICENSE
License-File: AUTHORS.md
Requires-Dist: numpy
Requires-Dist: numpyencoder
Requires-Dist: onnx
Requires-Dist: tensorflow; python_version <= "3.11"
Requires-Dist: pystache
Requires-Dist: onnxruntime
Provides-Extra: dev
Requires-Dist: ruff; extra == "dev"
Requires-Dist: mypy; extra == "dev"
Dynamic: license-file
